[
  {
    "k_number": "K200001",
    "success": true,
    "predicates": [
      "K171034"
    ],
    "similar_devices": [
      "K180912",
      "K181637",
      "K170277",
      "K171233",
      "K180599"
    ],
    "parent_devices": [],
    "child_devices": [],
    "timestamp": "2026-02-14T06:46:31.246541"
  },
  {
    "k_number": "K200002",
    "success": true,
    "predicates": [],
    "similar_devices": [],
    "parent_devices": [],
    "child_devices": [],
    "timestamp": "2026-02-14T07:06:58.722844"
  },
  {
    "k_number": "K200003",
    "success": true,
    "predicates": [],
    "similar_devices": [],
    "parent_devices": [],
    "child_devices": [],
    "timestamp": "2026-02-14T07:07:07.094439"
  },
  {
    "k_number": "K200005",
    "success": true,
    "predicates": [
      "K173785",
      "K182826"
    ],
    "similar_devices": [],
    "parent_devices": [],
    "child_devices": [],
    "timestamp": "2026-02-14T07:07:16.403630"
  },
  {
    "k_number": "K200007",
    "success": true,
    "predicates": [
      "K112150"
    ],
    "similar_devices": [],
    "parent_devices": [],
    "child_devices": [],
    "timestamp": "2026-02-14T07:07:24.219922"
  },
  {
    "k_number": "K200009",
    "success": true,
    "predicates": [],
    "similar_devices": [],
    "parent_devices": [],
    "child_devices": [],
    "timestamp": "2026-02-14T07:07:51.185409"
  },
  {
    "k_number": "K200010",
    "success": true,
    "predicates": [
      "K190222"
    ],
    "similar_devices": [],
    "parent_devices": [],
    "child_devices": [],
    "timestamp": "2026-02-14T07:07:59.212443"
  },
  {
    "k_number": "K200011",
    "success": true,
    "predicates": [
      "K150522",
      "K161190"
    ],
    "similar_devices": [],
    "parent_devices": [
      "K083116",
      "K892398",
      "K171181",
      "K061844"
    ],
    "child_devices": [],
    "timestamp": "2026-02-14T07:08:07.413292"
  },
  {
    "k_number": "K200015",
    "success": true,
    "predicates": [
      "K191769",
      "K103142"
    ],
    "similar_devices": [],
    "parent_devices": [],
    "child_devices": [],
    "timestamp": "2026-02-14T07:08:20.322652"
  },
  {
    "k_number": "K200016",
    "success": true,
    "predicates": [
      "K181414",
      "K172135"
    ],
    "similar_devices": [],
    "parent_devices": [],
    "child_devices": [],
    "timestamp": "2026-02-14T07:08:32.160721"
  },
  {
    "k_number": "K200017",
    "success": true,
    "predicates": [],
    "similar_devices": [],
    "parent_devices": [],
    "child_devices": [],
    "timestamp": "2026-02-14T07:08:54.937554"
  },
  {
    "k_number": "K200018",
    "success": true,
    "predicates": [],
    "similar_devices": [],
    "parent_devices": [],
    "child_devices": [],
    "timestamp": "2026-02-14T07:09:03.814856"
  },
  {
    "k_number": "K200019",
    "success": true,
    "predicates": [],
    "similar_devices": [],
    "parent_devices": [],
    "child_devices": [],
    "timestamp": "2026-02-14T07:09:07.973149"
  },
  {
    "k_number": "K200021",
    "success": true,
    "predicates": [
      "K070913"
    ],
    "similar_devices": [],
    "parent_devices": [],
    "child_devices": [],
    "timestamp": "2026-02-14T07:09:12.833081"
  },
  {
    "k_number": "K200022",
    "success": true,
    "predicates": [],
    "similar_devices": [],
    "parent_devices": [],
    "child_devices": [],
    "timestamp": "2026-02-14T07:09:21.957793"
  },
  {
    "k_number": "K200023",
    "success": true,
    "predicates": [
      "K894293"
    ],
    "similar_devices": [],
    "parent_devices": [],
    "child_devices": [],
    "timestamp": "2026-02-14T06:28:26.475633"
  },
  {
    "k_number": "K200024",
    "success": true,
    "predicates": [
      "K180925"
    ],
    "similar_devices": [],
    "parent_devices": [],
    "child_devices": [],
    "timestamp": "2026-02-14T07:10:36.099661"
  },
  {
    "k_number": "K200025",
    "success": true,
    "predicates": [],
    "similar_devices": [],
    "parent_devices": [],
    "child_devices": [],
    "timestamp": "2026-02-14T07:10:47.136866"
  },
  {
    "k_number": "K200026",
    "success": true,
    "predicates": [
      "K191428"
    ],
    "similar_devices": [],
    "parent_devices": [],
    "child_devices": [],
    "timestamp": "2026-02-14T06:49:45.533366"
  },
  {
    "k_number": "K200027",
    "success": true,
    "predicates": [
      "K172763",
      "K991088"
    ],
    "similar_devices": [],
    "parent_devices": [],
    "child_devices": [],
    "timestamp": "2026-02-14T06:49:56.444241"
  },
  {
    "k_number": "K200028",
    "success": true,
    "predicates": [
      "K162429",
      "K070882",
      "K013806",
      "K130033"
    ],
    "similar_devices": [],
    "parent_devices": [],
    "child_devices": [],
    "timestamp": "2026-02-14T06:50:02.577702"
  },
  {
    "k_number": "K200030",
    "success": true,
    "predicates": [
      "K172390"
    ],
    "similar_devices": [],
    "parent_devices": [],
    "child_devices": [],
    "timestamp": "2026-02-14T06:50:10.085166"
  },
  {
    "k_number": "K200031",
    "success": true,
    "predicates": [
      "K070180"
    ],
    "similar_devices": [],
    "parent_devices": [],
    "child_devices": [],
    "timestamp": "2026-02-14T06:50:26.299920"
  },
  {
    "k_number": "K200032",
    "success": true,
    "predicates": [
      "K160987"
    ],
    "similar_devices": [],
    "parent_devices": [],
    "child_devices": [],
    "timestamp": "2026-02-14T07:11:40.160191"
  },
  {
    "k_number": "K200033",
    "success": true,
    "predicates": [
      "K992704"
    ],
    "similar_devices": [],
    "parent_devices": [],
    "child_devices": [],
    "timestamp": "2026-02-14T07:11:46.807183"
  },
  {
    "k_number": "K200035",
    "success": true,
    "predicates": [
      "K182053"
    ],
    "similar_devices": [],
    "parent_devices": [],
    "child_devices": [],
    "timestamp": "2026-02-14T07:11:54.244977"
  },
  {
    "k_number": "K200036",
    "success": true,
    "predicates": [
      "K062282"
    ],
    "similar_devices": [
      "K113485"
    ],
    "parent_devices": [],
    "child_devices": [],
    "timestamp": "2026-02-14T07:12:04.050328"
  },
  {
    "k_number": "K200037",
    "success": true,
    "predicates": [
      "K142889"
    ],
    "similar_devices": [],
    "parent_devices": [
      "K103255"
    ],
    "child_devices": [],
    "timestamp": "2026-02-14T07:12:14.768742"
  },
  {
    "k_number": "K200038",
    "success": true,
    "predicates": [
      "K190639"
    ],
    "similar_devices": [],
    "parent_devices": [],
    "child_devices": [],
    "timestamp": "2026-02-14T07:12:24.463372"
  },
  {
    "k_number": "K200039",
    "success": true,
    "predicates": [
      "K102776"
    ],
    "similar_devices": [
      "K070991",
      "K101710"
    ],
    "parent_devices": [],
    "child_devices": [],
    "timestamp": "2026-02-14T07:12:32.070357"
  },
  {
    "k_number": "K200040",
    "success": true,
    "predicates": [
      "K180899"
    ],
    "similar_devices": [],
    "parent_devices": [],
    "child_devices": [],
    "timestamp": "2026-02-14T07:12:45.244250"
  },
  {
    "k_number": "K200041",
    "success": true,
    "predicates": [
      "K150473",
      "K141456"
    ],
    "similar_devices": [],
    "parent_devices": [],
    "child_devices": [],
    "timestamp": "2026-02-14T07:12:52.034026"
  },
  {
    "k_number": "K200042",
    "success": true,
    "predicates": [
      "K192528"
    ],
    "similar_devices": [],
    "parent_devices": [],
    "child_devices": [],
    "timestamp": "2026-02-14T07:12:58.455556"
  },
  {
    "k_number": "K200043",
    "success": true,
    "predicates": [
      "K051567",
      "K180348",
      "K083447",
      "K090522",
      "K141527",
      "K161616"
    ],
    "similar_devices": [],
    "parent_devices": [],
    "child_devices": [],
    "timestamp": "2026-02-14T07:13:06.030592"
  },
  {
    "k_number": "K200044",
    "success": true,
    "predicates": [],
    "similar_devices": [],
    "parent_devices": [],
    "child_devices": [],
    "timestamp": "2026-02-14T07:13:19.358967"
  },
  {
    "k_number": "K200045",
    "success": true,
    "predicates": [
      "K181778"
    ],
    "similar_devices": [],
    "parent_devices": [],
    "child_devices": [],
    "timestamp": "2026-02-14T07:13:26.790910"
  },
  {
    "k_number": "K200047",
    "success": true,
    "predicates": [
      "K171651"
    ],
    "similar_devices": [
      "K191100",
      "K162309",
      "K182417"
    ],
    "parent_devices": [],
    "child_devices": [],
    "timestamp": "2026-02-14T07:13:35.375868"
  },
  {
    "k_number": "K200048",
    "success": true,
    "predicates": [
      "K124034"
    ],
    "similar_devices": [
      "K160605",
      "K170455"
    ],
    "parent_devices": [],
    "child_devices": [],
    "timestamp": "2026-02-14T07:13:49.776512"
  },
  {
    "k_number": "K200049",
    "success": true,
    "predicates": [
      "K192877"
    ],
    "similar_devices": [],
    "parent_devices": [
      "K152848"
    ],
    "child_devices": [],
    "timestamp": "2026-02-14T07:13:56.822191"
  },
  {
    "k_number": "K200050",
    "success": true,
    "predicates": [
      "K190844"
    ],
    "similar_devices": [],
    "parent_devices": [],
    "child_devices": [],
    "timestamp": "2026-02-14T07:14:02.749526"
  },
  {
    "k_number": "K200051",
    "success": true,
    "predicates": [
      "K143263"
    ],
    "similar_devices": [],
    "parent_devices": [],
    "child_devices": [],
    "timestamp": "2026-02-14T07:14:14.129240"
  },
  {
    "k_number": "K200052",
    "success": true,
    "predicates": [
      "K172437"
    ],
    "similar_devices": [
      "K172437",
      "K172437"
    ],
    "parent_devices": [],
    "child_devices": [],
    "timestamp": "2026-02-14T07:14:22.439465"
  },
  {
    "k_number": "K200053",
    "success": true,
    "predicates": [
      "K111845"
    ],
    "similar_devices": [],
    "parent_devices": [],
    "child_devices": [],
    "timestamp": "2026-02-14T06:53:15.743367"
  },
  {
    "k_number": "K200056",
    "success": true,
    "predicates": [
      "K182083"
    ],
    "similar_devices": [
      "K182795"
    ],
    "parent_devices": [],
    "child_devices": [],
    "timestamp": "2026-02-14T06:53:28.657312"
  },
  {
    "k_number": "K200057",
    "success": true,
    "predicates": [],
    "similar_devices": [
      "K142056",
      "K172228",
      "K182965"
    ],
    "parent_devices": [],
    "child_devices": [],
    "timestamp": "2026-02-14T07:14:47.314736"
  },
  {
    "k_number": "K200060",
    "success": true,
    "predicates": [
      "K073326"
    ],
    "similar_devices": [],
    "parent_devices": [],
    "child_devices": [],
    "timestamp": "2026-02-14T07:14:53.927048"
  },
  {
    "k_number": "K200061",
    "success": true,
    "predicates": [
      "K133821",
      "K163105"
    ],
    "similar_devices": [],
    "parent_devices": [
      "K060390"
    ],
    "child_devices": [],
    "timestamp": "2026-02-14T07:15:02.279849"
  },
  {
    "k_number": "K200062",
    "success": true,
    "predicates": [
      "K102429",
      "K131093",
      "K152974",
      "K120359",
      "K060514",
      "K121601",
      "K100776",
      "K112583",
      "K191009"
    ],
    "similar_devices": [],
    "parent_devices": [],
    "child_devices": [],
    "timestamp": "2026-02-14T07:15:10.313474"
  },
  {
    "k_number": "K200063",
    "success": true,
    "predicates": [
      "K053605"
    ],
    "similar_devices": [],
    "parent_devices": [],
    "child_devices": [],
    "timestamp": "2026-02-14T07:15:19.532955"
  },
  {
    "k_number": "K200064",
    "success": true,
    "predicates": [
      "K110368",
      "K101860",
      "K082672"
    ],
    "similar_devices": [
      "K132071",
      "K110925",
      "K081558"
    ],
    "parent_devices": [],
    "child_devices": [],
    "timestamp": "2026-02-14T06:54:28.746008"
  },
  {
    "k_number": "K200065",
    "success": true,
    "predicates": [],
    "similar_devices": [],
    "parent_devices": [],
    "child_devices": [],
    "timestamp": "2026-02-14T07:15:45.371035"
  },
  {
    "k_number": "K200066",
    "success": true,
    "predicates": [
      "K151741",
      "K140046",
      "K163428"
    ],
    "similar_devices": [],
    "parent_devices": [],
    "child_devices": [],
    "timestamp": "2026-02-14T07:15:51.912685"
  },
  {
    "k_number": "K200067",
    "success": true,
    "predicates": [
      "K943052"
    ],
    "similar_devices": [],
    "parent_devices": [
      "K963524"
    ],
    "child_devices": [],
    "timestamp": "2026-02-14T06:55:02.343656"
  },
  {
    "k_number": "K200068",
    "success": true,
    "predicates": [
      "K132895"
    ],
    "similar_devices": [
      "K172052"
    ],
    "parent_devices": [
      "K052736"
    ],
    "child_devices": [],
    "timestamp": "2026-02-14T07:16:02.864400"
  },
  {
    "k_number": "K200069",
    "success": true,
    "predicates": [
      "K191279"
    ],
    "similar_devices": [
      "K113623"
    ],
    "parent_devices": [],
    "child_devices": [],
    "timestamp": "2026-02-14T07:16:11.859376"
  },
  {
    "k_number": "K200070",
    "success": true,
    "predicates": [
      "K151196"
    ],
    "similar_devices": [
      "K191575"
    ],
    "parent_devices": [],
    "child_devices": [],
    "timestamp": "2026-02-14T07:16:18.104610"
  },
  {
    "k_number": "K200071",
    "success": true,
    "predicates": [
      "K150852"
    ],
    "similar_devices": [],
    "parent_devices": [
      "K180068"
    ],
    "child_devices": [],
    "timestamp": "2026-02-14T07:16:25.355927"
  },
  {
    "k_number": "K200072",
    "success": true,
    "predicates": [
      "K182241",
      "K170686"
    ],
    "similar_devices": [],
    "parent_devices": [],
    "child_devices": [],
    "timestamp": "2026-02-14T07:16:36.465241"
  },
  {
    "k_number": "K200073",
    "success": true,
    "predicates": [
      "K181387"
    ],
    "similar_devices": [],
    "parent_devices": [],
    "child_devices": [],
    "timestamp": "2026-02-14T07:16:43.245638"
  },
  {
    "k_number": "K200074",
    "success": true,
    "predicates": [],
    "similar_devices": [],
    "parent_devices": [],
    "child_devices": [],
    "timestamp": "2026-02-14T07:16:53.092863"
  },
  {
    "k_number": "K200075",
    "success": true,
    "predicates": [
      "K103517"
    ],
    "similar_devices": [],
    "parent_devices": [
      "K170149"
    ],
    "child_devices": [],
    "timestamp": "2026-02-14T07:17:01.029339"
  },
  {
    "k_number": "K200076",
    "success": true,
    "predicates": [
      "K070858"
    ],
    "similar_devices": [],
    "parent_devices": [],
    "child_devices": [],
    "timestamp": "2026-02-14T07:17:09.521594"
  },
  {
    "k_number": "K200077",
    "success": true,
    "predicates": [
      "K181965"
    ],
    "similar_devices": [],
    "parent_devices": [
      "K101104"
    ],
    "child_devices": [],
    "timestamp": "2026-02-14T07:17:16.101544"
  },
  {
    "k_number": "K200078",
    "success": true,
    "predicates": [
      "K180629",
      "K152078"
    ],
    "similar_devices": [],
    "parent_devices": [],
    "child_devices": [],
    "timestamp": "2026-02-14T06:56:36.860139"
  },
  {
    "k_number": "K200079",
    "success": true,
    "predicates": [
      "K181195"
    ],
    "similar_devices": [],
    "parent_devices": [],
    "child_devices": [],
    "timestamp": "2026-02-14T07:17:33.516031"
  },
  {
    "k_number": "K200081",
    "success": true,
    "predicates": [
      "K173756"
    ],
    "similar_devices": [],
    "parent_devices": [
      "K130399"
    ],
    "child_devices": [],
    "timestamp": "2026-02-14T07:17:44.721531"
  },
  {
    "k_number": "K200082",
    "success": true,
    "predicates": [
      "K180236"
    ],
    "similar_devices": [],
    "parent_devices": [
      "K100288"
    ],
    "child_devices": [],
    "timestamp": "2026-02-14T06:57:01.687942"
  },
  {
    "k_number": "K200083",
    "success": true,
    "predicates": [
      "K171845"
    ],
    "similar_devices": [],
    "parent_devices": [],
    "child_devices": [],
    "timestamp": "2026-02-14T07:17:55.452239"
  },
  {
    "k_number": "K200084",
    "success": true,
    "predicates": [
      "K181246",
      "K150061",
      "K180076",
      "K122097"
    ],
    "similar_devices": [],
    "parent_devices": [],
    "child_devices": [],
    "timestamp": "2026-02-14T07:18:02.681674"
  },
  {
    "k_number": "K200087",
    "success": true,
    "predicates": [],
    "similar_devices": [],
    "parent_devices": [],
    "child_devices": [],
    "timestamp": "2026-02-14T07:18:08.954329"
  },
  {
    "k_number": "K200088",
    "success": true,
    "predicates": [
      "K080950"
    ],
    "similar_devices": [
      "K031017",
      "K053266"
    ],
    "parent_devices": [],
    "child_devices": [],
    "timestamp": "2026-02-14T07:18:25.994213"
  },
  {
    "k_number": "K200089",
    "success": true,
    "predicates": [
      "K161412"
    ],
    "similar_devices": [],
    "parent_devices": [],
    "child_devices": [],
    "timestamp": "2026-02-14T07:18:35.367433"
  },
  {
    "k_number": "K200090",
    "success": true,
    "predicates": [],
    "similar_devices": [],
    "parent_devices": [],
    "child_devices": [],
    "timestamp": "2026-02-14T07:18:46.386322"
  },
  {
    "k_number": "K200091",
    "success": true,
    "predicates": [],
    "similar_devices": [],
    "parent_devices": [],
    "child_devices": [],
    "timestamp": "2026-02-14T07:18:51.748762"
  },
  {
    "k_number": "K200092",
    "success": true,
    "predicates": [
      "K173437"
    ],
    "similar_devices": [],
    "parent_devices": [],
    "child_devices": [],
    "timestamp": "2026-02-14T07:19:03.375748"
  },
  {
    "k_number": "K200093",
    "success": true,
    "predicates": [],
    "similar_devices": [],
    "parent_devices": [],
    "child_devices": [],
    "timestamp": "2026-02-14T07:19:07.411683"
  },
  {
    "k_number": "K200094",
    "success": true,
    "predicates": [
      "K173662"
    ],
    "similar_devices": [],
    "parent_devices": [],
    "child_devices": [],
    "timestamp": "2026-02-14T07:19:13.557462"
  },
  {
    "k_number": "K200095",
    "success": true,
    "predicates": [
      "K140454"
    ],
    "similar_devices": [],
    "parent_devices": [
      "K173338"
    ],
    "child_devices": [],
    "timestamp": "2026-02-14T07:19:19.696608"
  },
  {
    "k_number": "K200096",
    "success": true,
    "predicates": [
      "K140566"
    ],
    "similar_devices": [],
    "parent_devices": [],
    "child_devices": [],
    "timestamp": "2026-02-14T07:19:28.486536"
  },
  {
    "k_number": "K200097",
    "success": true,
    "predicates": [
      "K161267"
    ],
    "similar_devices": [],
    "parent_devices": [
      "K181390"
    ],
    "child_devices": [],
    "timestamp": "2026-02-14T07:19:35.651162"
  },
  {
    "k_number": "K200098",
    "success": true,
    "predicates": [
      "K150883"
    ],
    "similar_devices": [],
    "parent_devices": [],
    "child_devices": [],
    "timestamp": "2026-02-14T07:19:42.325031"
  },
  {
    "k_number": "K200099",
    "success": true,
    "predicates": [
      "K153639"
    ],
    "similar_devices": [
      "K161689",
      "K171027",
      "K171694"
    ],
    "parent_devices": [],
    "child_devices": [],
    "timestamp": "2026-02-14T07:19:51.926231"
  },
  {
    "k_number": "K200100",
    "success": true,
    "predicates": [
      "K151455"
    ],
    "similar_devices": [],
    "parent_devices": [],
    "child_devices": [],
    "timestamp": "2026-02-14T07:19:59.293825"
  },
  {
    "k_number": "K200101",
    "success": true,
    "predicates": [
      "K182835"
    ],
    "similar_devices": [],
    "parent_devices": [],
    "child_devices": [],
    "timestamp": "2026-02-14T07:20:06.764885"
  },
  {
    "k_number": "K200102",
    "success": true,
    "predicates": [
      "K180282"
    ],
    "similar_devices": [
      "K192149",
      "K172505",
      "K163349",
      "K112162",
      "K140878"
    ],
    "parent_devices": [],
    "child_devices": [],
    "timestamp": "2026-02-14T07:20:17.636604"
  },
  {
    "k_number": "K200103",
    "success": true,
    "predicates": [],
    "similar_devices": [],
    "parent_devices": [],
    "child_devices": [],
    "timestamp": "2026-02-14T07:20:41.326728"
  },
  {
    "k_number": "K200104",
    "success": true,
    "predicates": [
      "K122237",
      "K030426",
      "K090762"
    ],
    "similar_devices": [],
    "parent_devices": [
      "K030883"
    ],
    "child_devices": [],
    "timestamp": "2026-02-14T07:20:48.811274"
  },
  {
    "k_number": "K200107",
    "success": true,
    "predicates": [
      "K061597",
      "K092849",
      "K093297",
      "K113726",
      "K171247"
    ],
    "similar_devices": [],
    "parent_devices": [],
    "child_devices": [],
    "timestamp": "2026-02-14T07:21:00.237528"
  },
  {
    "k_number": "K200108",
    "success": true,
    "predicates": [
      "K041287"
    ],
    "similar_devices": [],
    "parent_devices": [],
    "child_devices": [],
    "timestamp": "2026-02-14T07:21:06.943668"
  },
  {
    "k_number": "K200109",
    "success": true,
    "predicates": [
      "K991864",
      "K080592"
    ],
    "similar_devices": [],
    "parent_devices": [],
    "child_devices": [],
    "timestamp": "2026-02-14T07:21:14.722410"
  },
  {
    "k_number": "K200110",
    "success": true,
    "predicates": [],
    "similar_devices": [],
    "parent_devices": [],
    "child_devices": [],
    "timestamp": "2026-02-14T07:21:37.998726"
  },
  {
    "k_number": "K200112",
    "success": true,
    "predicates": [],
    "similar_devices": [],
    "parent_devices": [],
    "child_devices": [],
    "timestamp": "2026-02-14T07:01:38.055838"
  },
  {
    "k_number": "K200113",
    "success": true,
    "predicates": [],
    "similar_devices": [],
    "parent_devices": [],
    "child_devices": [],
    "timestamp": "2026-02-14T07:22:07.464593"
  },
  {
    "k_number": "K200114",
    "success": true,
    "predicates": [
      "K141581"
    ],
    "similar_devices": [],
    "parent_devices": [],
    "child_devices": [],
    "timestamp": "2026-02-14T07:22:15.552923"
  },
  {
    "k_number": "K200115",
    "success": true,
    "predicates": [
      "K173077"
    ],
    "similar_devices": [
      "K172064",
      "K172320",
      "K142041",
      "K153097"
    ],
    "parent_devices": [],
    "child_devices": [],
    "timestamp": "2026-02-14T07:22:20.929739"
  },
  {
    "k_number": "K200116",
    "success": true,
    "predicates": [
      "K191685",
      "K173700"
    ],
    "similar_devices": [],
    "parent_devices": [],
    "child_devices": [],
    "timestamp": "2026-02-14T07:02:08.591600"
  },
  {
    "k_number": "K200117",
    "success": true,
    "predicates": [
      "K192207"
    ],
    "similar_devices": [],
    "parent_devices": [],
    "child_devices": [],
    "timestamp": "2026-02-14T07:22:41.160644"
  },
  {
    "k_number": "K200118",
    "success": true,
    "predicates": [
      "K172193"
    ],
    "similar_devices": [],
    "parent_devices": [],
    "child_devices": [],
    "timestamp": "2026-02-14T07:22:49.183728"
  },
  {
    "k_number": "K200119",
    "success": true,
    "predicates": [
      "K173555"
    ],
    "similar_devices": [
      "K170445",
      "K192159",
      "K161843",
      "K190442"
    ],
    "parent_devices": [],
    "child_devices": [],
    "timestamp": "2026-02-14T07:22:58.358507"
  },
  {
    "k_number": "K200120",
    "success": true,
    "predicates": [
      "K170684"
    ],
    "similar_devices": [],
    "parent_devices": [],
    "child_devices": [],
    "timestamp": "2026-02-14T07:23:04.856012"
  },
  {
    "k_number": "K213241",
    "success": true,
    "predicates": [
      "K133817"
    ],
    "similar_devices": [],
    "timestamp": "2026-02-14T03:03:39.855930"
  },
  {
    "k_number": "K214829",
    "success": false,
    "error": "Extraction failed",
    "timestamp": "2026-02-14T03:02:42.423292"
  },
  {
    "k_number": "K221234",
    "success": true,
    "predicates": [
      "K220674"
    ],
    "similar_devices": [],
    "parent_devices": [],
    "child_devices": [],
    "timestamp": "2026-02-14T03:17:16.802512"
  },
  {
    "k_number": "K230746",
    "success": true,
    "predicates": [
      "K080684"
    ],
    "similar_devices": [],
    "parent_devices": [],
    "child_devices": [],
    "timestamp": "2026-02-14T03:17:40.773134"
  },
  {
    "k_number": "K232318",
    "success": true,
    "predicates": [],
    "similar_devices": [],
    "parent_devices": [],
    "child_devices": [],
    "timestamp": "2026-02-14T03:17:13.152499"
  },
  {
    "k_number": "K241542",
    "success": true,
    "predicates": [
      "K233814"
    ],
    "similar_devices": [],
    "parent_devices": [],
    "child_devices": [],
    "timestamp": "2026-02-14T03:17:36.884324"
  },
  {
    "k_number": "K242714",
    "success": true,
    "predicates": [],
    "similar_devices": [],
    "parent_devices": [],
    "child_devices": [],
    "timestamp": "2026-02-14T03:20:17.999774"
  },
  {
    "k_number": "K243824",
    "success": true,
    "predicates": [
      "K220823"
    ],
    "similar_devices": [
      "K222044",
      "K200100",
      "K193352"
    ],
    "parent_devices": [
      "K183518"
    ],
    "child_devices": [],
    "timestamp": "2026-02-14T03:16:50.723600"
  }
]